hs_pyrender-0.2.0.dev1.data/data/lib/site-packages/pyrender/libraries/2d_drawCalls.dll
hs_pyrender-0.2.0.dev1.data/data/lib/site-packages/pyrender/libraries/3d_drawCalls.dll
pyrender/__init__.py
pyrender/core.py
pyrender/vectors.py
hs_pyrender-0.2.0.dev1.dist-info/LICENSE
hs_pyrender-0.2.0.dev1.dist-info/METADATA
hs_pyrender-0.2.0.dev1.dist-info/WHEEL
hs_pyrender-0.2.0.dev1.dist-info/top_level.txt
hs_pyrender-0.2.0.dev1.dist-info/RECORD
