Metadata-Version: 2.1
Name: hs-pyrender
Version: 0.2.0.dev1
Summary: A rendering Library made in python
Home-page: https://github.com/HotShot0901/PyRender
Author: Arnav Choudhary
Author-email: contact.hot.shor.1234@gmail.com
License: MIT
Keywords: render PyRender 3d
Platform: UNKNOWN
Classifier: Development Status :: 3 - Alpha
Classifier: Programming Language :: Python :: 3
Classifier: License :: OSI Approved :: MIT License
Classifier: Operating System :: Microsoft :: Windows
Requires-Python: >=3.6
Requires-Dist: opencv-python
Requires-Dist: numpy
